matlab_nbconvert
