Metadata-Version: 1.1
Name: matlab-nbconvert
Version: 0.3
Summary: An exporter for matlab-based jupyter notebooks
Home-page: https://github.com/janfreyberg/matlab_nbconvert
Author: Jan Freyberg
Author-email: jan.freyberg@gmail.com
License: MIT
Download-URL: https://github.com/janfreyberg/matlab_nbconvert/tarball/0.3
Keywords: matlab,jupyter,notebook,nbconvert
Platform: UNKNOWN
Classifier: Development Status :: 3 - Alpha
Classifier: Intended Audience :: Science/Research
Classifier: Topic :: Software Development :: Code Generators
Classifier: License :: OSI Approved :: MIT License
Classifier: Programming Language :: Python :: 3.4
Classifier: Programming Language :: Python :: 3.5
